linkedin_profile_pic/__init__.py
linkedin_profile_pic/cli.py
linkedin_profile_pic-0.2.2.dist-info/LICENSE.txt
linkedin_profile_pic-0.2.2.dist-info/METADATA
linkedin_profile_pic-0.2.2.dist-info/WHEEL
linkedin_profile_pic-0.2.2.dist-info/entry_points.txt
linkedin_profile_pic-0.2.2.dist-info/top_level.txt
linkedin_profile_pic-0.2.2.dist-info/RECORD
