Metadata-Version: 2.1
Name: linkedin_profile_pic
Version: 0.2.2
Summary: A tool to download LinkedIn profile pictures
Home-page: https://github.com/yourusername/linkedin_profile_pic
Author: Ishant Dahiya
Author-email: ishantdahiya@gmail.com
Project-URL: Bug Tracker, https://github.com/yourusername/linkedin_profile_pic/issues
Classifier: Programming Language :: Python :: 3
Classifier: License :: OSI Approved :: MIT License
Classifier: Operating System :: OS Independent
Requires-Python: >=3.6
License-File: LICENSE.txt
Requires-Dist: selenium
Requires-Dist: requests
Requires-Dist: click
Requires-Dist: tqdm
Requires-Dist: webdriver-manager
